apisports/__init__.py
apisports/_client.py
apisports/data.py
apisports/response.py
apisports/data/baseball-v1.yaml
apisports/data/basketball-v1.yaml
apisports/data/football-v3.yaml
apisports/data/formula1-v1.yaml
apisports/data/hockey-v1.yaml
apisports/data/rugby-v1.yaml
apisports-0.3.1.dist-info/LICENSE
apisports-0.3.1.dist-info/METADATA
apisports-0.3.1.dist-info/WHEEL
apisports-0.3.1.dist-info/top_level.txt
apisports-0.3.1.dist-info/RECORD
