Metadata-Version: 2.1
Name: apisports
Version: 0.3.1
Summary: UNKNOWN
Home-page: https://github.com/MikeSmithEU/apisports/
Author: MikeSmithEU
Author-email: projects@mikesmith.eu
License: UNKNOWN
Platform: any
Classifier: Programming Language :: Python
Classifier: Programming Language :: Python :: 3
Requires-Python: >=3.6
License-File: LICENSE
Requires-Dist: tqdm (==4.32.2)
Requires-Dist: requests (==2.22.0)
Requires-Dist: pyyaml (==5.4.1)
Requires-Dist: m2r (==0.2.1)
Provides-Extra: test
Requires-Dist: pytest (<=3.10.1,>=2.8.0) ; extra == 'test'
Requires-Dist: requests-mock (>=1.9) ; extra == 'test'
Requires-Dist: pycodestyle ; extra == 'test'
Requires-Dist: pytest-cov ; extra == 'test'
